pytensordb/__init__.py
pytensordb/async_util.py
pytensordb/comm_api_cli.py
pytensordb/comm_util.py
pytensordb/example.py
pytensordb/vsepy/.DS_Store
pytensordb/vsepy/__init__.py
pytensordb/vsepy/_comm_util.py
pytensordb/vsepy/libvsepy_cimp.so
pytensordb/vsepy/vsepy_cimp.dll
pytensordb/vsepy/vsepy_cimp.exp
pytensordb/vsepy/vsepy_cimp.lib
pytensordb/vsepy/__pycache__/__init__.cpython-37.pyc
pytensordb/vsepy/__pycache__/__init__.cpython-39.pyc
pytensordb/vsepy/__pycache__/_comm_util.cpython-37.pyc
pytensordb/vsepy/__pycache__/_comm_util.cpython-39.pyc
pytensordb-1.0.0.dist-info/LICENSE
pytensordb-1.0.0.dist-info/METADATA
pytensordb-1.0.0.dist-info/WHEEL
pytensordb-1.0.0.dist-info/top_level.txt
pytensordb-1.0.0.dist-info/RECORD
