Metadata-Version: 2.1
Name: pytensordb
Version: 1.0.0
Summary: TensorDB API(Python)
Home-page: https://www.actionsky.com/Cloud-tree-series/tensordb.html
Author: 上海爱可生信息技术股份有限公司
Author-email: zhoupeng@actionsky.com
License: Apache LICENSE 2.0
Platform: UNKNOWN
Classifier: License :: OSI Approved :: MIT License
Classifier: Programming Language :: Python
Classifier: Programming Language :: Python :: 3
Classifier: Programming Language :: Python :: 3.9
Classifier: Programming Language :: Python :: Implementation :: CPython
Classifier: Programming Language :: Python :: Implementation :: PyPy
Classifier: Topic :: Software Development :: Libraries
License-File: LICENSE
